um/__init__.py
um/collections/__init__.py
um/collections/binary_search_tree.py
um/crypto/__init__.py
um/crypto/cipher.py
um/statistics/__init__.py
um/utils.py
um/visuals/__init__.py
um/visuals/color.py
um-1.5.2.dist-info/LICENSE
um-1.5.2.dist-info/WHEEL
um-1.5.2.dist-info/METADATA
um-1.5.2.dist-info/RECORD
