Metadata-Version: 2.1
Name: um
Version: 1.5.2
Summary: 
License: MIT
Author: umatbro
Author-email: umatbroo@gmail.com
Requires-Python: >=3.7,<4.0
Classifier: License :: OSI Approved :: MIT License
Classifier: Programming Language :: Python :: 3
Classifier: Programming Language :: Python :: 3.7
Requires-Dist: numpy (>=1.17,<2.0)
Requires-Dist: pandas (>=0.25.3,<0.26.0)
